{
  "navigationBarTitleText": "AI创作",
  "navigationStyle": "custom",
  "enablePullDownRefresh": false,
  "onReachBottomDistance": 50,
  "backgroundTextStyle": "dark",
  "backgroundColor": "#f5f7fa",
  "usingComponents": {
    "t-icon": "tdesign-miniprogram/icon/icon",
    "t-button": "tdesign-miniprogram/button/button",
    "t-textarea": "tdesign-miniprogram/textarea/textarea",
    "t-image": "tdesign-miniprogram/image/image",
    "t-toast": "tdesign-miniprogram/toast/toast",
    "t-dialog": "tdesign-miniprogram/dialog/dialog"
  }
} 